[
    {
        "_id": "111",
        "name": "Tai Chi for Cognition",
        "publishDate": "MAY 24, 2018",
        "description": "The studies suggest Tai Chi has impacts on global cognitive functions, visuospatial skills, semantic memor...",
        "imageURL": "https://i.postimg.cc/XNrQGS7y/blog-1.jpg"
    },
    {
        "_id": "222",
        "name": "Special Geriatrics Care",
        "publishDate": "MAY 24, 2018",
        "description": "eriatrics or geriatric medicine is a speciality that is based on improving health care for elderly people...",
        "imageURL": "https://i.postimg.cc/v8CX5qc2/blog-2.jpg"
    },
    {
        "_id": "333",
        "name": "Care for Senior People",
        "publishDate": "MAY 24, 2018",
        "description": "Elderly care, or simply eldercare serves the needs and requirements of senior citizens. It encompasses assisted living...",
        "imageURL": "https://i.postimg.cc/MpmD2ztg/blog-3.jpg"
    },
    {
        "_id": "444",
        "name": "4 Ways to Use Virtual Care",
        "publishDate": "MAY 24, 2018",
        "description": "With healthcare shifting more into virtual care, providers and patients need to feel comfortable with the use of technology...",
        "imageURL": "https://i.postimg.cc/c4YhhR3x/blog-4.jpg"
    },
    {
        "_id": "555",
        "name": "Grown by Nature",
        "publishDate": "MAY 24, 2018",
        "description": "Grown By Nature's supplements have been proven, through extensive research, to be better than anything else. Our supplements are...",
        "imageURL": "https://i.postimg.cc/vm8vGCNT/blog-5.jpg"
    },
    {
        "_id": "666",
        "name": "Healthy Lifestyle",
        "publishDate": "MAY 24, 2018",
        "description": "A healthy lifestyle simply means doing things that make you happy and feel good. For one person, that may mean walking...",
        "imageURL": "https://i.postimg.cc/Vk8RVJ9j/blog-6.jpg"
    }
]